malama/__init__.py
malama/fileParse/__init__.py
malama/fileParse/base.py
malama/fileParse/claude.py
malama/fileParse/cohere.py
malama/fileParse/context.py
malama/fileParse/deepseek.py
malama/fileParse/exceptions.py
malama/fileParse/gemini.py
malama/fileParse/groq.py
malama/fileParse/mistral.py
malama/fileParse/openai.py
malama/fileParse/reader.py
malama/fileParse/togetherai.py
malama-0.1.6.dist-info/licenses/LICENSE
malama-0.1.6.dist-info/METADATA
malama-0.1.6.dist-info/WHEEL
malama-0.1.6.dist-info/top_level.txt
malama-0.1.6.dist-info/RECORD
