Metadata-Version: 2.4
Name: malama
Version: 0.1.6
Summary: Universal document assistant using popular AI models (PDF, Word, Excel)
Home-page: 
Author: Manoj Prajapati
Author-email: manojbittu161@gmail.com
Classifier: Programming Language :: Python :: 3
Classifier: License :: OSI Approved :: MIT License
Classifier: Operating System :: OS Independent
Classifier: Intended Audience :: Developers
Classifier: Topic :: Text Processing :: General
Classifier: Topic :: Office/Business :: Office Suites
Classifier: Topic :: Scientific/Engineering :: Artificial Intelligence
Requires-Python: >=3.6
License-File: LICENSE
Requires-Dist: pymupdf
Requires-Dist: google-generativeai
Requires-Dist: anthropic
Requires-Dist: python-docx
Requires-Dist: openpyxl
Dynamic: author
Dynamic: author-email
Dynamic: classifier
Dynamic: description
Dynamic: description-content-type
Dynamic: license-file
Dynamic: requires-dist
Dynamic: requires-python
Dynamic: summary
